[
    {
        "user_id": 2,
        "order_number": "ORD-20260429-001",
        "subtotal": 164.98,
        "tax": 16.5,
        "shipping_cost": 10,
        "total": 191.48,
        "status": "shipped",
        "payment_status": "paid",
        "payment_method": "card",
        "id": 1
    },
    {
        "id": 2,
        "order_number": "ORD-20260505-002",
        "user_id": 5,
        "user_name": "sae",
        "user_email": "dignatheobard960@gmail.com",
        "status": "shipped",
        "payment_status": "paid",
        "payment_method": "Vodacom M-Pesa",
        "subtotal": 89.98,
        "tax": 6.3,
        "shipping_cost": 24,
        "total": 120.28,
        "created_at": "2026-05-05 10:48:42"
    },
    {
        "id": 3,
        "order_number": "ORD-20260507-003",
        "user_id": 7,
        "user_name": "Dee",
        "user_email": "deetheo04@gmail.com",
        "status": "shipped",
        "payment_status": "paid",
        "payment_method": "Airtel Money\n\nAirtel Money",
        "subtotal": 823,
        "tax": 57.61,
        "shipping_cost": 24,
        "total": 904.61,
        "created_at": "2026-05-07 08:14:44"
    }
]